simpledqn/__init__.py
simpledqn/dqn_agent.py
simpledqn-0.1.dist-info/METADATA
simpledqn-0.1.dist-info/WHEEL
simpledqn-0.1.dist-info/top_level.txt
simpledqn-0.1.dist-info/RECORD
