Metadata-Version: 2.4
Name: simpledqn
Version: 0.1
Summary: A simple DQN implementation for reinforcement learning beginners
Author: Shiv Shah
Author-email: shivshah1917@gmail.com
Requires-Dist: torch>=1.9.0
Requires-Dist: gymnasium
Requires-Dist: matplotlib
Dynamic: author
Dynamic: author-email
Dynamic: description
Dynamic: description-content-type
Dynamic: requires-dist
Dynamic: summary
